restrapid/__init__.py
restrapid/management/__init__.py
restrapid/management/commands/__init__.py
restrapid/management/commands/rapidrest.py
RapidRest-0.1.4.dist-info/LICENSE
RapidRest-0.1.4.dist-info/METADATA
RapidRest-0.1.4.dist-info/WHEEL
RapidRest-0.1.4.dist-info/top_level.txt
RapidRest-0.1.4.dist-info/RECORD
