Metadata-Version: 2.1
Name: RapidRest
Version: 0.1.4
Summary: A Django package to quickly generate serializers and views for Django models
Home-page: 
Author: shubham chavan
Author-email: shubhamchavan7920@gmail.com
Classifier: Programming Language :: Python :: 3
Classifier: License :: OSI Approved :: MIT License
Classifier: Operating System :: OS Independent
Requires-Python: >=3.6
License-File: LICENSE
Requires-Dist: Django >=3.2
